[
    {
        "author": "Alexia",
        "title": "Dame Amor (Gimme Love)",
        "text": [
            [
                "Dame amor",
                "Dame baby dame dame amor",
                "Dame amor",
                "Dame dame amor",
                "Baby dame tu amor"
            ],
            [
                "Te quiero amor",
                "Yo recuerdo que nos vimos",
                "Y no pense te importaria de mi",
                "Luego hablamos un momento",
                "Sin imaginar que seria asi"
            ],
            [
                "Dame tu amor"
            ],
            [
                "",
                "Te necesito",
                "Dame tu amor",
                "Y tu carino"
            ],
            [
                "No se porque",
                "Cuando estamos separados",
                "Nada existe en este mundo sin ti",
                "Pues hay algo que me mata",
                "Siempre que te siento cerca de mi"
            ],
            [
                "Dame amor"
            ]
        ]
    },
    {
        "author": "Alexia",
        "title": "Number One (Spanish Version)",
        "text": [
            [
                "QUIERO ABRAZARTE BABY"
            ],
            [
                "QUIERO ABRAZARTE",
                "NUNCA MAS SOLO SI A MI LADO ESTAS",
                "PUEDES VENIR COSAS QUE NECESITAS"
            ],
            [
                "SE QUE ME VAS A AMAR",
                "LO ESTOY SINTIENDO CON TODA MI PIEL",
                "DESNUDA TUS SENTIMIENTOS",
                "MUESTRAME EL MODO Y YO TE HARE ESTAR BIEN",
                "ENAMORANDOME"
            ],
            [
                "I WANNA BE YOUR NUMBER ONE",
                "SOLO SIN NADIE MAS",
                "Y TU SERAS MI LOCO AMOR",
                "YA NO TE PODRE DEJAR"
            ],
            [
                "NO QUIERO PERDERTE",
                "YO SE QUE NUNCA ME VAS A HACER MAL",
                "PUEDES VENIR CONMIGO",
                "YO TENGO LAS COSAS QUE NECESITAS",
                "ENAMORANDOME"
            ],
            [
                "I WANNA BE YOUR NUMBER ONE",
                "SOLO SIN NADIE MAS",
                "Y TU SERAS MI LOCO AMOR",
                "YA NO TE PODRE DEJAR"
            ],
            [
                "I WANNA BE YOUR NUMBER ONE",
                "SOLO SIN NADIE MAS",
                "Y TU SERAS MI LOCO AMOR",
                "YA NO TE PODRE DEJAR"
            ],
            [
                "I WANNA BE YOUR NUMBER ONE",
                "LA LA LA LA LA LA",
                "I WANNA BE YOUR NUMBER ONE",
                "LA LA LA LA LA LA"
            ],
            [
                "QUIERO ABRAZARTE BABY"
            ],
            [
                "I WANNA BE YOUR NUMBER ONE",
                "SOLO SIN NADIE MAS",
                "Y TU SERAS MI LOCO AMOR",
                "YA NO TE PODRE DEJAR"
            ],
            [
                "I WANNA BE YOUR NUMBER ONE",
                "SOLO SIN NADIE MAS",
                "Y TU SERAS MI LOCO AMOR",
                "YA NO TE PODRE DEJAR"
            ],
            [
                "I WANNA BE YOUR NUMBER ONE"
            ]
        ]
    }
]