[
    {
        "author": "Los Actors",
        "title": "Antes De Morir",
        "text": [
            [
                "Tal vez no pueda sentir tu respiración",
                "tal vez no podre vivir lo que fue ayer",
                "todo lo que quise ser se fue y no vendrá",
                "y antes de morir aquí",
                "me veras caer"
            ],
            [
                "Siente como el agua en aire se me va",
                "Siente como el frío no regresara ja-más",
                "dime si volver a amar es igual",
                "tu miedo sigue en mi yo sigo en ti aun que no puedas mas."
            ],
            [
                "Tal vez no podre volver a respirar por ti",
                "Tal vez no podre tener mis manos en ti",
                "Todo lo que quise ser se fue y no vendra",
                "y antes de morir aquí me veras caer."
            ],
            [
                "Siente como el agua en aire se me va",
                "Siente come el frio no regresara jamas",
                "Dime si volver a amar es igual",
                "Tu miedo sigue en mi y yo sigo en ti aun que no puedas más"
            ],
            [
                "Siente como el agua en aiare se me va",
                "Siente como e el frio no regresara ja-mas",
                "Dime si volver a amar es igual",
                "Tu miedo sigue en mi y yo sigo en ti aun que no puedas más"
            ]
        ]
    },
    {
        "author": "Los Actors",
        "title": "Ayer",
        "text": [
            [
                "Llévame contigo a donde quieras que yo este",
                "aunque no estés...",
                "Déjame atado por cien años",
                "sin saber en donde estoy"
            ],
            [
                "Y ha sido aquí donde no pasa nada,",
                "y ha sido aquí donde no pasa nada..",
                "Y ha sido aquí donde no pasa nada,",
                "y ha sido aquí donde no pasa nada",
                "donde no pasa nada!!"
            ],
            [
                "Quiéreme",
                "y dime todo lo que tengas que decir...",
                "Ódiame,",
                "hasta que tus deseos de volver ya no estén"
            ],
            [
                "Y ha sido aquí donde no pasa nada,",
                "y ha sido aquí donde no pasa nada..",
                "Y ha sido aquí donde no pasa nada,",
                "y ha sido aquí donde no pasa nada",
                "donde no pasa nada!!"
            ],
            [
                "Y así pasar",
                "un día mas sin Sol,",
                "un día sin saber que terminaba así.",
                "Y todo vuelve a ser,",
                "y todo vuelve a ser",
                "y todo vuelve,",
                "y todo vuelve",
                "y vuelve igual que ayer"
            ],
            [
                "Y así pasar",
                "un día mas sin Sol,",
                "un día sin saber que terminaba así.",
                "Y todo vuelve a ser,",
                "y todo vuelve a ser",
                "y todo vuelve,",
                "y todo vuelve",
                "y vuelve igual que ayer"
            ],
            [
                "Un día mas sin Sol,",
                "un día sin saber que terminaba así.",
                "Y todo vuelve a ser,",
                "y todo vuelve a ser",
                "y todo vuelve,",
                "y todo vuelve",
                "y vuelve igual que ayer"
            ]
        ]
    },
    {
        "author": "Los Actors",
        "title": "Deja Que Llueva",
        "text": [
            [
                "Si me atreviera a confesar todo",
                "Lo que pienso de ti al despertar",
                "Si yo pudiera respirar tan cerca de",
                "Ti me robaría tus sueños"
            ],
            [
                "Ahora me tienes aquí deja que el",
                "Tiempo se encargue de ti solo esta",
                "Vez estarás tan cerca de mí que",
                "Podrás olvidarlo róbame el viento",
                "Cierra los ojos y yo en un momento estaré",
                "Dentro de ti dentro del sol"
            ],
            [
                "Déjame estar otra vez dentro de ti",
                "Dentro del sol deja que llueva otra",
                "Vez dentro de ti dentro del sol"
            ],
            [
                "Róbame el viento ooo, ooo cierra",
                "Los ojos y yo en un momento estaré",
                "Dentro de ti dentro del sol"
            ],
            [
                "Déjame estar otra vez dentro de ti",
                "Dentro del sol deja que llueva otra",
                "Vez dentro de ti dentro del sol"
            ],
            [
                "Déjame estar otra vez dentro de ti",
                "Dentro del sol deja que llueva otra",
                "Vez dentro de ti dentro del sol"
            ]
        ]
    },
    {
        "author": "Los Actors",
        "title": "Descúbreme",
        "text": [
            [
                "Para ir a donde estas tú",
                "yo necesito mas mi sed",
                "de tenerte entre mis manos",
                "y tocarte hasta los pies"
            ],
            [
                "Aquí ya,",
                "ya no hay más,",
                "ya no existe la verdad",
                "que algún día volveré.."
            ],
            [
                "Solo el tiempo puede hacer:"
            ],
            [
                "Niegame",
                "como tu lo haces",
                "y ayúdame a alejarme de ti.",
                "Óyeme",
                "aunque ya no puedas mas",
                "descubreme,",
                "descubreme otra vez,",
                "descubreme otra.."
            ],
            [
                "Pierdeme",
                "como tu lo haces",
                "y ayúdame a alejarme de ti.",
                "Óyeme",
                "aunque ya no puedas más",
                "descubreme",
                "descubreme otra vez,",
                "descubreme otra vez,",
                "descubreme otra vez,",
                "descubreme otra vez,",
                "descubreme otra,",
                "descubreme otra,",
                "descubreme otra."
            ]
        ]
    },
    {
        "author": "Los Actors",
        "title": "Ilusión",
        "text": [
            [
                "Mírame por última vez para que no",
                "Te olvides de mi este es el final de",
                "Un día que nunca empezó este es el dolor",
                "Que un día nunca termino y ahora",
                "Se va ya no regresara"
            ],
            [
                "Solo entre tu amor y a sido solo una Ilusión",
                "Donde cada vez más y más te vas yendo",
                "Solo entre tu amor y ha sido solo una ilusión",
                "Donde cada vez más y más te vas yendo amor"
            ],
            [
                "Mírame y llévame otra vez a aquel lugar",
                "Que nunca morirá este es el final de un",
                "Día que nunca empezó este es el dolor",
                "Que un día nunca termino y ahora",
                "Se va ya no regresara"
            ],
            [
                "Solo entre tu amor y ha sido solo una Ilusión",
                "Donde cada vez más y más te vas yendo",
                "Solo entre tu amor y ha sido solo una ilusión",
                "Donde cada vez más y más te vas yendo amor"
            ],
            [
                "Solo entre tu amor y ha sido solo una Ilusión",
                "Donde cada vez más y más te vas yendo",
                "Solo entre tu amor y ha sido solo una ilusión",
                "Donde cada vez más y más te vas yendo amor"
            ]
        ]
    },
    {
        "author": "Los Actors",
        "title": "Lo Que Tú Quieres",
        "text": [
            [
                "Ya no quiero estar aquí",
                "toma ya,",
                "toma tus cosas si ya puedes volar."
            ],
            [
                "Solo dime una vez",
                "lo que ya,",
                "lo que esta muerto ya no puede volar."
            ],
            [
                "Así eres tú!!...",
                "Ahora soy yo!!!!!"
            ],
            [
                "Porque no tengo que escucharte mas,",
                "porque no tengo que besarte ya,",
                "porque no tengo que hacer lo que tu quieres!!"
            ],
            [
                "Porque no tengo que abrazarte mas,",
                "porque no tengo que mirarte ya,",
                "porque no tengo que hacer lo que tu quieres!!!"
            ],
            [
                "Ya no quiero estar aya",
                "toma ya,",
                "toma tus cosas si ya puedes volar."
            ],
            [
                "Solo dime esta vez",
                "lo que ya,",
                "lo que esta muerto ya no puede volar."
            ],
            [
                "Así eres tú!!...",
                "Ahora soy yo!!!!!"
            ],
            [
                "Porque no tengo que escucharte mas,",
                "porque no tengo que besarte ya,",
                "porque no tengo que hacer lo que tu quieres!!"
            ],
            [
                "Porque no tengo que abrazarte mas,",
                "porque no tengo que mirarte ya,",
                "porque no tengo que hacer lo que tu quieres!!!"
            ]
        ]
    },
    {
        "author": "Los Actors",
        "title": "Mírame",
        "text": [
            [
                "Mirame a los ojos",
                "dime si me quieres besar",
                "uuuooohhh",
                "Deja que te lleve por un mundo que no es normal",
                "uuuooohhh"
            ],
            [
                "Hoy",
                "te veo cambiar de piel,",
                "esto no",
                "ya no es como ayer",
                "nada es como ayer"
            ],
            [
                "Mirame a los ojos,",
                "dime si me quieres besar",
                "uuuooohhh"
            ],
            [
                "Deja que te lleve por un mundo que no es normal",
                "uuuooohhh",
                "Besame por dentro",
                "y arrancame el corazon",
                "uuuooohhh"
            ],
            [
                "Quedate en silencio",
                "y dime lo que ya no es verdad",
                "uuuooohhh ooohhh"
            ],
            [
                "Hoy",
                "ya no esta con alll...",
                "no,yo puedo ser",
                "Quien te lleve hasta el fin."
            ],
            [
                "Solo,mirame a los ojos",
                "dime si me quieres besar",
                "Deja que te lleve por un mundo que no es normal"
            ],
            [
                "Besame por dentro",
                "y arrancame el corazon."
            ],
            [
                "Quedate en silencio,",
                "y dime lo que ya no es verdad"
            ],
            [
                "Mirame a los ojos,",
                "dime si me quieres besar",
                "uuuooohhh"
            ],
            [
                "Deja que te lleve por un mundo que no es normal",
                "uuuooohhh"
            ],
            [
                "Besame por dentro,",
                "y arrancame el corazon",
                "uuuooohhh"
            ],
            [
                "Quedate en silencio y dime lo que ya no es verdad",
                "uuuooohhh"
            ],
            [
                "Ven amor,dejalo,solo yo",
                "puedo hacerte sentir,solo ven amor,",
                "besame",
                "solo tu puedes hacerme sentir como ayer!!!"
            ]
        ]
    },
    {
        "author": "Los Actors",
        "title": "Miente",
        "text": [
            [
                "Miénteme amor deja que yo respire tu maldad",
                "Miénteme amor hasta que yo no pueda respirar",
                "Si aquellas luces dejan de brillar"
            ],
            [
                "Es por tu aliento que no deja de mentir",
                "Es tu deseo el que me invita a morir",
                "Es por tus dientes donde nace el veneno de tu ser",
                "Es tu deseo de morder toda mi piel",
                "Es tu deseo el que me invita a morir",
                "Es tu deseo que me invita a morir"
            ],
            [
                "Quiéreme amor quiéreme mas mientras",
                "Me vez llorar quiéreme amor deja que yo",
                "Respire tu verdad si aquellas luces dejan",
                "De brillar"
            ],
            [
                "Es por tu aliento que no deja de mentir",
                "Es tu deseo el que me invita a morir",
                "Es por tus dientes donde nace el veneno de tu ser",
                "Es tu deseo de morder toda mi piel",
                "Es tu deseo el que me invita a morir",
                "Es tu deseo que me invita a morir"
            ]
        ]
    },
    {
        "author": "Los Actors",
        "title": "Sé Que No (Un Lugar Para Dormir)",
        "text": [
            [
                "Aqui no estoy",
                "Aqui me vi,volviendo del ayer,",
                "El sol salio y empiezo a ver,",
                "Que tu no estas ahy."
            ],
            [
                "Dejame estar cerca de ti,",
                "No ves puedo morir,",
                "Dejame amarte una vez mas,",
                "Una antes de partir",
                "Uuuhh,aaahhh,uuuhhh,aaahhh."
            ],
            [
                "Llevame a donde quieras tu,",
                "Yo se que no hay dolor",
                "A un lugar dentro de ti"
            ],
            [
                ",",
                "Para poder dormir,",
                "Para poder dormir,",
                "Para poder dormir",
                "Ooohhh",
                "Podras sentir",
                "Uuuhhh,",
                "Podras volver,",
                "Uuuhhh,",
                "Podras vivir,",
                "Uuuhhh,",
                "Podras morir,",
                "Iiieeehhh."
            ],
            [
                "Se que no,yo se que no podras sentir",
                "Se que no,yo se que no podras volver",
                "Se que no,yo se que no podras vivir",
                "Se que no,yo se que no podras morir."
            ]
        ]
    }
]