[
    {
        "author": "Paghania",
        "title": "Fiesta Vikinga",
        "text": [
            [
                "Ya ha llegado el día,"
            ],
            [
                "Ven, estamos de fiesta,"
            ],
            [
                "Nada deja sobre sus suertes,"
            ],
            [
                "Celebramos con mucho alcohol"
            ],
            [
                "Ven a la batalla"
            ],
            [
                "Que tuvimos que enfrentar,"
            ],
            [
                "Hemos quemado todo un pueblo,"
            ],
            [
                "Sigamos sin parar"
            ],
            [
                "Espadas en tus garras,"
            ],
            [
                "Descansan ya en paz,"
            ],
            [
                "Cervezas color de oro,"
            ],
            [
                "Heladas como Asgard"
            ],
            [
                "Mujeres muy ardientes"
            ],
            [
                "Te esperan en el hogar"
            ],
            [
                "El cielo y la tierra"
            ],
            [
                "Verán estremecer el mar"
            ],
            [
                "Vamos a brindar"
            ],
            [
                "En la fiesta vikinga,"
            ],
            [
                "No veas hacia el cielo,"
            ],
            [
                "Vamos a empuñar"
            ],
            [
                "De no estar uno bien,"
            ],
            [
                "Beberé por la victoria,"
            ],
            [
                "Demasiada sangre"
            ],
            [
                "Se hizo derramar"
            ],
            [
                "Vamos a brindar"
            ],
            [
                "En la fiesta vikinga,"
            ],
            [
                "No veas hacia el cielo,"
            ],
            [
                "Vamos a empuñar"
            ],
            [
                "De no estar uno bien,"
            ],
            [
                "Beberé por la victoria,"
            ],
            [
                "Demasiada sangre"
            ],
            [
                "Se hizo derramar"
            ]
        ]
    },
    {
        "author": "Paghania",
        "title": "La Cosecha",
        "text": [
            [
                "Temprano en la mañana ha cantado el gallo"
            ],
            [
                "La noche ya se ha ido a montar los caballos"
            ],
            [
                "El padre, el hijo y los perros a su lado"
            ],
            [
                "Momento de partir a recorrer el campo"
            ],
            [
                "El turno de la tierra ha concluido"
            ],
            [
                "Los frutos ya maduros en su estilo"
            ],
            [
                "Duro trabajo de campesinos"
            ],
            [
                "Son obras de arte con flores de olivo"
            ],
            [
                "Fue dura la fecha al llegar este dia"
            ],
            [
                "Las lluvias destrozaron cultivos de familia"
            ],
            [
                "El cielo se enfermó durante varios meses"
            ],
            [
                "Las flores murieron sin crecer fervientes"
            ],
            [
                "Cuando el viento sopla del norte"
            ],
            [
                "Trae consigo hojas e ilusiones"
            ],
            [
                "Cuando la luna llena está"
            ],
            [
                "La cosecha crece más de lo normal"
            ],
            [
                "A pesar del tiempo que llevó este esfuerzo"
            ],
            [
                "Fue fundamental la ayuda de ancestros"
            ],
            [
                "Espiritus del bosque interfirieron"
            ],
            [
                "En mejorar el clima de este desierto"
            ],
            [
                "La oscuridad cubrió las sierras y el manantial"
            ],
            [
                "Sobre las tierras de Paghania se ha de sembrar"
            ],
            [
                "Wohooooooooooooo..."
            ],
            [
                "Wohooooooooooooo..."
            ]
        ]
    },
    {
        "author": "Paghania",
        "title": "Recuerdos De Guerra",
        "text": [
            [
                "Sangre guerrera corre por tus venas"
            ],
            [
                "Pero hay una fuerza de ser en mí"
            ],
            [
                "Busco respuestas, pero no encuentro"
            ],
            [
                "Sólo la luna me refleja en tí"
            ],
            [
                "El puño, mi espada y me lanzo a luchar"
            ],
            [
                "La muerte es fuerte, pero no va a llegar"
            ],
            [
                "Ríos de sangre aquí correrán"
            ],
            [
                "Viendo el dolor de tu honor"
            ],
            [
                "Las hordas se acercan para matar"
            ],
            [
                "Sonidos de guerra en mi alma sonarán"
            ],
            [
                "Con mi espada me lanzo a luchar"
            ],
            [
                "Sólo el miedo sale vivo de mí"
            ],
            [
                "Siento las muestras de valor"
            ],
            [
                "Y los llantos de temor"
            ],
            [
                "El cielo se abre en nombre de Odín"
            ],
            [
                "Mi alma en el Valhalla se forjará"
            ],
            [
                "En nombre de Odín, debe morir"
            ],
            [
                "Dejando el destino dentro de mí"
            ],
            [
                "El Valhalla sus puertas tendrá"
            ],
            [
                "Para las almas puedan seguir"
            ],
            [
                "Espada en tu nombre y lo vaciaré"
            ],
            [
                "Se acerca la luz de libertad"
            ],
            [
                "Desde el cielo te observaré"
            ],
            [
                "Y tu alma entregaré"
            ],
            [
                "En medio del combate cuando voy a estar"
            ],
            [
                "Al borde de la muerte y llegarás a él"
            ],
            [
                "Recuerdos de infancias llenos de poder"
            ],
            [
                "Siente su fuerza y vuelve a luchar"
            ],
            [
                "Su espada empuñada siempre estará"
            ],
            [
                "Para la sangre que aquí correrá"
            ],
            [
                "Él no es de su pueblo, dice el guardián"
            ],
            [
                "De las almas y la libertad"
            ],
            [
                "En nombre de Odín, debe morir"
            ],
            [
                "Dejando el destino dentro de mí"
            ],
            [
                "El Valhalla sus puertas tendrá"
            ],
            [
                "Para las almas puedan seguir"
            ],
            [
                "Espada en tu nombre y lo vaciaré"
            ],
            [
                "Se acerca la luz de libertad"
            ],
            [
                "Desde el cielo te observaré"
            ],
            [
                "Y tu alma entregaré"
            ]
        ]
    },
    {
        "author": "Paghania",
        "title": "Santuario Del Puma",
        "text": [
            [
                "Cuando veo el cielo"
            ],
            [
                "Que corre, se despejarán,"
            ],
            [
                "Las nubes longevas se marcharán"
            ],
            [
                "Y las estrellas se asomarán"
            ],
            [
                "Iluminando mi oscuro pasar"
            ],
            [
                "Escarcha cubre las hojas"
            ],
            [
                "El suave rocio que cubre mi piel"
            ],
            [
                "Bajo dejando huellas"
            ],
            [
                "Mi hogar he dejado en busca de luz"
            ],
            [
                "Montañas que la neblina"
            ],
            [
                "No vea en sus pies"
            ],
            [
                "Sus faldas cobijan un manantial"
            ],
            [
                "Fuerza de vida, poder floral"
            ],
            [
                "Osamentos al despertar..."
            ],
            [
                "Alerce, lugar vital,"
            ],
            [
                "Santuario en el bosque, poder floral,"
            ],
            [
                "Orgullo de muchos seres,"
            ],
            [
                "Humanos comparten tu viejo historial"
            ],
            [
                "Me interno en el río, torrente fluvial"
            ],
            [
                "Sus aguas heladas me intentan sanar"
            ],
            [
                "¡Santuario sagrado del mundo!"
            ],
            [
                "Cuando veo el cielo"
            ],
            [
                "Que corre, se despejarán"
            ],
            [
                "Las nubes longevas se marcharan"
            ],
            [
                "Y las estrellas se asomaran"
            ],
            [
                "Woooooooo..."
            ],
            [
                "Montañas que la neblina"
            ],
            [
                "No vea en sus pies"
            ],
            [
                "Sus faldas cobijan un manantial"
            ],
            [
                "Fuerza de vida, poder floral"
            ],
            [
                "Woooooooo..."
            ]
        ]
    }
]