[
    {
        "author": "Righeira",
        "title": "La Musica Electronica",
        "text": [
            [
                "Un ritmo nuevo a todo el pueblo",
                "Sonido lindo che mi calma el Niño",
                "Ma che musica... es diabolica...",
                "Es la musica e-electronica"
            ],
            [
                "En un segundo reinizia el mundo",
                "Computadora para mi señora",
                "Ma che musica... es diabolica...",
                "Es la musica e-electronica"
            ],
            [
                "Es la musica e-electronica",
                "Es mi musica..."
            ],
            [
                "Un ipnotismo en todo el cosmo",
                "Sonido lindo che mi tocca el mango",
                "Ma che musica... es diabolica...",
                "Es la musica e-electronica"
            ],
            [
                "Es la musica e-electronica",
                "Es mi musica..."
            ],
            [
                "Ma che musica... es diabolica...",
                "Es la musica e-electronica",
                "Ma che musica... es diabolica...",
                "Es la musica e-electronica"
            ]
        ]
    },
    {
        "author": "Righeira",
        "title": "No Tengo Dinero",
        "text": [
            [
                "No tengo dinero, oh",
                "No tengo dinero no, no, no, no",
                "No tengo dinero, oh",
                "No tengo dinero no, no, no, no"
            ],
            [
                "Los modernos lujos viven aquí",
                "En el lugar más alto de mi ciudad",
                "Se nutren de imágenes y de relais",
                "Yo quisiera estar ahí más"
            ],
            [
                "No tengo dinero, oh",
                "No tengo dinero no, no, no, no",
                "No tengo dinero, oh",
                "No tengo dinero no, no, no, no"
            ],
            [
                "Los nuevos italianos crean aquí",
                "Impávidos y fieros de la velocidad",
                "Neo psichico es el sintético edén",
                "Yo quisiera estar ahí más"
            ],
            [
                "No tengo dinero, oh",
                "No tengo dinero no, no, no, no",
                "No tengo dinero, oh",
                "No tengo dinero no, no, no, no"
            ],
            [
                "Neo psichico",
                "Besado de una dea tu eres",
                "Patria de estos te crean",
                "Patria de estos te crean"
            ],
            [
                "No tengo dinero, oh",
                "No tengo dinero no, no, no, no",
                "No tengo dinero, oh",
                "No tengo dinero no, no, no, no"
            ]
        ]
    },
    {
        "author": "Righeira",
        "title": "Vamos a la playa",
        "text": [
            [
                "Vamos a la playa, oh o-o-o-oh",
                "Vamos a la playa, oh o-o-o-oh",
                "Vamos a la playa, oh o-o-o-oh",
                "Vamos a la playa, oh oh"
            ],
            [
                "Vamos a la playa",
                "La bomba estallo",
                "Las radiaciones tuestan",
                "Y matizan de azul"
            ],
            [
                "Vamos a la playa, oh o-o-o-oh",
                "Vamos a la playa, oh o-o-o-oh",
                "Vamos a la playa, oh o-o-o-oh",
                "Vamos a la playa, oh oh"
            ],
            [
                "Vamos a la playa",
                "Todos con sombrero",
                "El viento radiactivo",
                "Despeina los cabellos"
            ],
            [
                "Vamos a la playa, oh oh oh oh oh",
                "Vamos a la playa, oh oh oh oh oh",
                "Vamos a la playa, oh oh oh oh oh",
                "Vamos a la playa, oh oh"
            ],
            [
                "Vamos a la playa, oh o-o-o-oh",
                "Vamos a la playa, oh o-o-o-oh",
                "Vamos a la playa, oh o-o-o-oh",
                "Vamos a la playa, oh oh"
            ],
            [
                "Vamos a la playa",
                "Al fin el mar es limpio",
                "No mas peces hediondos",
                "Sino agua florecente"
            ],
            [
                "Vamos a la playa, oh o-o-o-oh",
                "Vamos a la playa, oh o-o-o-oh",
                "Vamos a la playa, oh o-o-o-oh",
                "Vamos a la playa, oh oh"
            ],
            [
                "Vamos a la playa, oh o-o-o-oh",
                "Vamos a la playa, oh o-o-o-oh",
                "Vamos a la playa, oh o-o-o-oh",
                "Vamos a la playa, oh o-o-o-oh",
                "Vamos a la playa, oh o-o-o-oh",
                "Vamos a la playa, oh o-o-o-oh",
                "Vamos a la playa, oh o-o-o-oh"
            ]
        ]
    }
]