[
    {
        "author": "Sin Espina",
        "title": "14 A 22",
        "text": [
            [
                "Dando vueltas por ahi",
                "Del camino me escapé",
                "Tu veneno me hizo bien",
                "De 14 a 22"
            ],
            [
                "Tus colmillos de marfil",
                "Mis venitas de papel",
                "Tu cagazo de vivir",
                "Voy 14 a 22"
            ],
            [
                "Quiero verte naufragar",
                "Desde este cristal",
                "Donde nada es real",
                "Y no hay nada que ocultar"
            ],
            [
                "El velorio del patin",
                "Del banquete del placer",
                "Tengo ganas de salir",
                "De 14 a 22"
            ],
            [
                "Gente tibia por aquí",
                "Sus problemas son de ayer",
                "Sigo solo en mi motin",
                "Soy 14 a 22"
            ],
            [
                "Quiero verte naufragar",
                "Desde este cristal",
                "Donde nada es real",
                "Y no hay nada que ocultar"
            ]
        ]
    },
    {
        "author": "Sin Espina",
        "title": "Aletas",
        "text": [
            [
                "Aletas de dolor",
                "Quieto bajo el sol",
                "Sintiendo que es",
                "Un ser afortunado"
            ],
            [
                "El puede mirar",
                "Su tiempo manejar",
                "Pero el no deja",
                "De ser juzgado, condenado"
            ],
            [
                "En al inocencia mojar",
                "De placer a otros"
            ],
            [
                "Libre de pensar",
                "El pude llegar",
                "Donde la natura",
                "Lo permita"
            ],
            [
                "Conoce su ley",
                "Hay más grandes que él",
                "Dios de esa manera",
                "Lo ha pactado, alado"
            ],
            [
                "Pero el astuto",
                "No va a dejar que lo atrapen"
            ],
            [
                "Libre de pensar",
                "El pude llegar",
                "Donde la natura",
                "Lo permita"
            ],
            [
                "Conoce su ley",
                "Hay mas grandes que él",
                "Dios de esa manera",
                "Lo ha partado, alado"
            ],
            [
                "En la inocencia mojar",
                "De placer..."
            ]
        ]
    },
    {
        "author": "Sin Espina",
        "title": "Asiento Transero",
        "text": [
            [
                "Los cerebros juegan con la humanidad",
                "De manera peligrosa",
                "Tené cuidado con tu propia libertad",
                "Sos uncerebro más"
            ],
            [
                "Ansiedad de ilusión y deseo",
                "Todo se funde en el asiento trasero"
            ],
            [
                "Condenados a la ruina material",
                "Festejando los empates",
                "Hoy los tajos no te dejan respirar",
                "Sos un muñeco más"
            ],
            [
                "Ansiedad, ilusión y deseo",
                "Todo se funde en el asiento trasero"
            ]
        ]
    },
    {
        "author": "Sin Espina",
        "title": "Carnovo",
        "text": [
            [
                "Viendo los embrollos de la gente",
                "Me pregunto ¿les resulta indiferente?",
                "No me explico en qué momento te perdí",
                "Conciencia vuelve a mí"
            ],
            [
                "Rompiéndome las manos pro pavadas",
                "Escondiéndome en guitarras yo me fui",
                "Esperando el toque exacto de la nada",
                "Paciencia vuele a mi"
            ],
            [
                "Estoy sin salir",
                "Estoy sin dormir",
                "Estoy buscando la manera",
                "De meterme en tu vida"
            ],
            [
                "Hablando con mi alma me apuñalo",
                "Me cuestiona si en algo yo caí",
                "Tal vez quise pretender que sea perfecto",
                "Demencia vuelve a mi"
            ],
            [
                "Estoy sin salir",
                "Estoy sin dormir",
                "Estoy buscando la manera",
                "De meterme en tu vida"
            ]
        ]
    },
    {
        "author": "Sin Espina",
        "title": "Do",
        "text": [
            [
                "Finde ansiosa al mundo cruel",
                "Su aventura y su perdición",
                "Riñe a gusto de su papel",
                "La macabra prosperidad"
            ],
            [
                "Noche y ruido de motor",
                "Con luces pegadas a la piel",
                "Buscasin miedo satisfacción",
                "La mentira ya llegara..."
            ],
            [
                "Llora su gracia al amanecer"
            ],
            [
                "Llora si gracia en soledad",
                "Y corta su viaje con más",
                "Y promesas que no vendrán",
                "Sombras bajas en la pared"
            ],
            [
                "Sombras bajas en la pared",
                "Pájaro libre torturándote"
            ],
            [
                "Mira pronto su sombra actual",
                "Sin caricias en su pasión",
                "Se endurece de solo pensar",
                "Que la vida lo dejo atrás"
            ],
            [
                "Mala poción abogándolo",
                "Mala poción, mala poción"
            ]
        ]
    },
    {
        "author": "Sin Espina",
        "title": "Fábula",
        "text": [
            [
                "Soy la más fuerte",
                "Mi filo corta y mata",
                "Mentira dijo el árbol",
                "Y al fin murió de espaldas"
            ],
            [
                "Amenazó la piedra",
                "Yo soy pesada y llena",
                "La espalda ya sin filo",
                "Prevaleció despierta"
            ],
            [
                "No me importa el rollo de los demás",
                "Ya no me importan muchas cosas",
                "Si yo pudiera tu destino cambiar",
                "Si yo pudiera ver el sol no intentaría despegar"
            ],
            [
                "Su necia valentía",
                "Quizo ofender al agua",
                "Se zambulló al destino",
                "Quebrando toda calma"
            ],
            [
                "Sin decir nada",
                "Mantuvo su paciencia",
                "Su natural esencia",
                "Puso oxidar su alma"
            ],
            [
                "No me importa el rollo de los demás",
                "Ya no me importan muchas cosas",
                "Si yo pudiera tu destino cambiar",
                "Si yo pudiera ver el sol no intentaría despegar"
            ],
            [
                "Soy la más fuerte",
                "Mi filo corta y mata",
                "Se zambulló al destino",
                "Logró oxidar su alma"
            ]
        ]
    },
    {
        "author": "Sin Espina",
        "title": "Igual A Los Demás",
        "text": [
            [
                "Podes estar fumando un caño en al popular",
                "Salir de alguna fiesta con el tajo principal",
                "Tener un puto carro para ir a boludear",
                "Vivir en una casa con amor y lo demás"
            ],
            [
                "Podés estar en naca masticando la verdad",
                "Cayendo en el pasado a toda velocidad",
                "Pidiéndole a cualquier estatua en la catedral",
                "Comprarte un perro nuevo para ir a caminar"
            ],
            [
                "Podes mirar el noticiero",
                "Y ver que sos igual a los demás",
                "Podés bajar del patrullero",
                "Y ver que sos igual a los demás"
            ],
            [
                "Podés estar en naca masticando la verdad",
                "Cayendo en el pasado a toda velocidad",
                "Pidiéndole a cualquier estatua en la catedral",
                "Comprarte un perro nuevo para ir a caminar"
            ],
            [
                "Podés mirar el noticiero",
                "Y ver que sos igual a los demás",
                "Podés bajar del patrullero",
                "Y ver que sos igual a los demás"
            ],
            [
                "Hace tanto que aprendiste a caminar",
                "Cuantas veces vas a tropezar",
                "Ves muy fácil el problema en los demás",
                "Con vos perdés objetividad"
            ],
            [
                "Podés mirar el noticiero",
                "Y ver que sos igual a los demás",
                "Podés salir de tu agujero",
                "Y ver que sos igual a los demás",
                "Podés hacerte el cuchillero",
                "Y ver que sos igual a los demás",
                "Podés tener dos torres a los demás",
                "Y ver que sos igual a los demás",
                "Podés perder tu ptrullero",
                "Y ver que sos igual a los demás"
            ]
        ]
    },
    {
        "author": "Sin Espina",
        "title": "La Matando",
        "text": [
            [
                "Ella tenía un amigo",
                "El tenía un corazón",
                "Ella ponía los puntos",
                "El ponía lo mejor"
            ],
            [
                "El se tentaba verla",
                "Dentro del camisón",
                "Mientras ella planeaba",
                "Estretagías del amor"
            ],
            [
                "Por darle besos a las ratas",
                "Mordiste el queso sin saber",
                "Tapando mugre con cagadas",
                "Dejaste todo son hacer"
            ],
            [
                "El siempre iba y venía",
                "Como canario en jaulón",
                "Cuando la otra le dijo",
                "Elegí el corazon"
            ],
            [
                "Con su libertad perdida",
                "El miedo le chifló",
                "La confianza cedía",
                "Y surgió lo peor"
            ],
            [
                "Por darle besos a las ratas",
                "Mordiste el queso sin saber",
                "Tapando mugre con cagadas",
                "Dejaste todo son hacer"
            ]
        ]
    },
    {
        "author": "Sin Espina",
        "title": "Postre y Nada Más",
        "text": [
            [
                "Me queda larga la birra",
                "Me queda largo el colchón",
                "Me quedan largos los caños",
                "Me quedó lleno el jarrón",
                "Me queda lo que dice el viento",
                "Al corazón"
            ],
            [
                "Me quedan cortos los días",
                "Me queda largo el garrón",
                "Me queda corta la noche",
                "Me queda largo el salón",
                "Me queda irme todo el tiempo",
                "Hasta dónde voy"
            ],
            [
                "Me queda el postre y nada más",
                "Me quedó el puesto en el collar del fin"
            ],
            [
                "Me queda lejos la mierda",
                "Me queda cerca el jamón",
                "Me queda firme la tierra",
                "Me queda corto el bajón",
                "Me queda lo que tengo adentro",
                "Del pantalón"
            ],
            [
                "Me queda corta la vida",
                "Me queda largo el cajón",
                "Me ves que vendo la rifa",
                "Me ves que guardo el talón",
                "Me ves que vivo como quiero",
                "Y te da terror"
            ],
            [
                "Anoche yo te vi rezar",
                "Hablabas con el más allá"
            ],
            [
                "Me queda el postre y nada más",
                "Me quedó puesto en el collar del fin"
            ]
        ]
    },
    {
        "author": "Sin Espina",
        "title": "Sin Timón",
        "text": [
            [
                "No soy un barco sin timón",
                "No tengo rumbo",
                "Juego con un ascensor",
                "Y una montaña que",
                "Subo cuando quiero yo",
                "Y no me aburro",
                "Y bajo a convidarte a vos",
                "Y te convido bien"
            ],
            [
                "En ese mundo de ilusión",
                "De los normales",
                "Venden por televisión",
                "Esa mascota que",
                "Llora ríe sin razón",
                "Si está en el aire",
                "Y nunca enseñan la lección",
                "Para agarrarte bien"
            ],
            [
                "Soy de una generación",
                "De rocanrroles",
                "Vivo bajo la presión",
                "De haber vivido bien",
                "Siempre quiero ser pichón",
                "De faraones",
                "Siempre el tiempo es el ladrón",
                "Nosotros cómplices"
            ],
            [
                "Veo sogas con arpón",
                "Por todos lados",
                "Sé que no sos del montón",
                "Sentís la misma sed",
                "Dame un poco de emoción",
                "Que estoy quemado",
                "Alquilame el corazón",
                "Yo te lo pago bien"
            ],
            [
                "Estoy feliz de ser quien soy",
                "Aunque no debe hacer",
                "Eso que hago en el rincón",
                "De la miseria bien",
                "Puede ser que vea el sol",
                "En una noche asó",
                "No te rias más de mí",
                "Que en este océano..."
            ],
            [
                "Somos barcos sin timón",
                "Sufriendoo el mundo",
                "Si entiendes que no hay opción",
                "Tenés que hacerlo bien",
                "Aguantarse el rocanrrol",
                "Es un laburo",
                "Te acordás que viste el sol",
                "Y lo tapaste bien"
            ]
        ]
    },
    {
        "author": "Sin Espina",
        "title": "Sol",
        "text": [
            [
                "Mi corazón no es algo gris",
                "Se justifica en la razón",
                "Tu corazón no va a cambiar",
                "Se transfigura la pasión"
            ],
            [
                "La traición es algo cruel",
                "El tiempo lo va a superar",
                "Con las heridas aún abiertas",
                "Ya está lista"
            ],
            [
                "Tu condición no es de olvidar",
                "Solo hay que dejar pasar",
                "No busques más, no quieras ser",
                "La más perdida del lugar"
            ],
            [
                "Tu corazón no va a cambiar",
                "Si late al ritmo de tu nariz",
                "Golpea más el viento audaz",
                "Si estas en ruta y vas a mil"
            ]
        ]
    },
    {
        "author": "Sin Espina",
        "title": "Una Locura Mejor",
        "text": [
            [
                "Vivo solo desde que",
                "Tu canción me hizo ver",
                "Que cuando el rio suena",
                "Trar agua que me moja los pies"
            ],
            [
                "Miro fijo en el parquet",
                "Siento risas de bebés",
                "Mi bondi esta vacio",
                "Por que solo a mi me deja bien"
            ],
            [
                "Tengo que esperar",
                "Tengo que esperar el sol",
                "Tengo que buscar",
                "Tengo que encontrar mi voz",
                "Estar tan solo es quizás",
                "Una locura menor"
            ],
            [
                "Esqueletos del papel",
                "Siempre vuelven a nacer",
                "No quiero reventarme la cabeza",
                "Contra el almacén"
            ],
            [
                "Sos el dueño del cartel",
                "Sos la ruina del plantel",
                "Mejor si dejo todo",
                "Y vuelvo a ser lo que fui alguna vez"
            ],
            [
                "Tengo que frenar",
                "Tengo que esperar el sol",
                "Tengo que gritar",
                "Tengo que encontrar mi voz"
            ],
            [
                "Estar tan loco es quizás",
                "Una postura mejor",
                "Estar tan solo es quizás",
                "Una locura menor",
                "Estar tan loco quizás",
                "Una locura menos..."
            ]
        ]
    },
    {
        "author": "Sin Espina",
        "title": "Vida Chatarra",
        "text": [
            [
                "Basta de comer basura",
                "Basta de mirar la luna",
                "Tu vieja esta leyendo",
                "Revistas de actualidad"
            ],
            [
                "Basta de escuchar basura",
                "Basta de decir locuras",
                "Tu nena esta robando",
                "Lo que no debe probar"
            ],
            [
                "La vida es una sola",
                "Y vos comés lo que encontraste en la mesa",
                "Nunca vas a saber cocinar"
            ],
            [
                "Basta de coger sin ganas",
                "Basta de quemas semanas",
                "Tu perro esta volada",
                "Todo lo que hace es ladrar"
            ],
            [
                "Basta de esperar sin milagros",
                "Basta de aguantar extraños",
                "La cena está quemándose",
                "En tu cocina de atrás"
            ],
            [
                "La vida es una sola",
                "Y vos comés lo que encontraste en la mesa",
                "Nunca vas a saber cocinar"
            ]
        ]
    }
]