[
    {
        "author": "Valentino",
        "title": "Morir de Amor",
        "text": [
            [
                "[Magnate]",
                "Aaaaaaaaaaay...",
                "Que malo es morir de amor... (Morir de amor...),",
                "Por esa niña hermosa moriria why me ha robado el corazon"
            ],
            [
                "AaAaAaAaAay...",
                "Que malo es morir de amor...",
                "Por esa niña hermosa moriria, why me ha robado el corazon...",
                "(Oye, mami te estas dando guille conmigo[Tu me sigues...]",
                "Esto es lo ultimo q te voy a decir...)"
            ],
            [
                "[Arcángel]",
                "Ven con el nene(Si)",
                "Yo se meterle(Obligao)",
                "Donde te metas, voy a meterte (Tu lo sabes)",
                "Ven conmigo, ellos no sabe entenderte (Nop)",
                "Tengo musica buena para complacerte (Uhu)",
                "Tengo por mango agarrao el sarten,(Yeah)",
                "Austin ¨La Maravish¨",
                "They call me captain",
                "America!!!",
                "O como tu quiera",
                "Me encanta esa gata cuando se pone histerica (Tu me sigue!?)"
            ],
            [
                "Si yo pudiera",
                "Te daria la vida entera...",
                "Contigo me fuera",
                "A un lugar especial",
                "Mami quiciera",
                "Pasar la noche entera",
                "Tu why yo solos en vela",
                "Viviendo un amor de novela..."
            ],
            [
                "[Magnate]",
                "Aaaaaaaaaaay...",
                "Que malo es morir de amor... (Morir de amor...),",
                "Por esa niña hermosa moriria why me ha robado el corazon"
            ],
            [
                "AaAaAaAaAay...",
                "Que malo es morir de amor...",
                "Por esa niña hermosa moriria, why me ha robado el corazon..."
            ],
            [
                "Quiero entragarme",
                "Ser dueño de tus partes",
                "Para olvidarme why sentirme en un mundo aparte..."
            ],
            [
                "Umm ya lo veras Oh Baby",
                "Umm ya lo veras...",
                "Esta noche es Tuya",
                "Te doy mas why mas",
                "Oh oh oh..."
            ],
            [
                "Umm ya lo veras Oh baby",
                "Umm ya lo veras...",
                "Umm ya lo veras Oh baby",
                "Te doy mas why mas",
                "Oh oh oh..."
            ],
            [
                "Umm ya lo veras Oh baby",
                "Umm ya lo veras...",
                "Umm ya lo veras Oh baby",
                "Te doy mas why mas",
                "Oh oh oh..."
            ],
            [
                "Aaaaaaaaaaay...",
                "Que malo es morir de amor... (Morir de amor...),",
                "Por esa niña hermosa moriria why me ha robado el corazon"
            ],
            [
                "AaAaAaAaAay...",
                "Que malo es morir de amor...",
                "Por esa niña hermosa moriria, why me ha robado el corazon..."
            ],
            [
                "[Arcángel]",
                "Yes..",
                "Esto es?",
                "Los Brother",
                "Magnate,Valentino",
                "Y...",
                "Austin ¨La Maravish¨"
            ],
            [
                "[Valentino]",
                "Esto solamente son Los Brother (Da ca dap da?)",
                "Imaginate...",
                "Nuestra Produccion...(Da cap dap da da...)",
                "El Comeback",
                "Aguanta..."
            ],
            [
                "[Arcángel]",
                "Jajaja...",
                "V.I. Music?",
                "Oye...",
                "Santana ?The Golden Boy?",
                "El Niño de oro...",
                "A Neldy",
                "Tu Me Sigues!?",
                "Siganos q les conviene",
                "Jaja",
                "Alex Gargola",
                "Da ca dap da?",
                "Prrrra!!!"
            ]
        ]
    },
    {
        "author": "Valentino",
        "title": "Presión",
        "text": [
            [
                "Alright stick em up",
                "Don, reportandose para los bandoleros",
                "Valen...tino",
                "Escobar"
            ],
            [
                "Esta noche tu no podras escapar",
                "Se que ante mi declaro te vas a rendir",
                "Ya lo veras, asi que decide si konmigo te vas",
                "Veras que de mi te dejaras llevar",
                "Escobar el del contrabando musical"
            ],
            [
                "Eo vengan gatas pidan accion",
                "Voy azotarlas con tu reggaeton come on",
                "Eo \"(dale que yo aguanto la accion)",
                "si veras que saco presion presion",
                "Eo vengan gatas pidan accion",
                "Voy azotarlas con tu reggaeton come on",
                "Eo \"(dale que yo aguanto la accion)",
                "si veras que saco presion presion"
            ],
            [
                "Coman de mi mela-suria",
                "Ellas piden action y les doy con furia",
                "Que se jodann si hablan de mi susten-tulia",
                "Hoy habra reggeaton bajo sol o lluvia",
                "Pega rubia.. no lo tolero",
                "Soy un bandolero de los meros mero",
                "Por el vecindario no me desespero",
                "Espero mi turno y soy mas sertero",
                "Los mate fekero"
            ],
            [
                "Gata no te amarres deja que te agarre",
                "No te pongas ruda sere mas amable",
                "Si tu gato llega puede que se endiable",
                "Y no cojan de su combo pa que to estos puercos se embarren",
                "Gata no te amarres deja que te agarre",
                "No te pongas ruda sere mas amable",
                "Si tu gato llega puede que se endiable",
                "Y no cojan de su combo pa que to estos puercos se embarren"
            ],
            [
                "Eo vengan gatas pidan accion",
                "Voy azotarlas con tu reggaeton come on",
                "Eo \"(dale que yo aguanto la accion)",
                "si veras que saco presion presion",
                "Eo vengan gatas pidan accion",
                "Voy azotarlas con tu reggaeton come on",
                "Eo \"(dale que yo aguanto la accion)",
                "si veras que saco presion presion"
            ],
            [
                "Ahora tu cucala y aprietala",
                "Dejala que coja viaje",
                "Bailale y sujetala",
                "Dale duro no te rajes",
                "Atrevete y besala",
                "Que esa ya borro un millage",
                "Cuidao si te enchula que de eso ella sabe",
                "Ahora tu cucala y aprietala",
                "Dejala que coja viaje",
                "Bailale y sujetala",
                "Dale duro no te rajes",
                "Atrevete y besala",
                "Que esa ya borro un millage",
                "Cuidao si te enchula que de eso ella sabe"
            ],
            [
                "Eo vengan gatas pidan accion",
                "Voy azotarlas con tu reggaeton come on",
                "Eo \"(dale que yo aguanto la accion)",
                "si veras que saco presion presion",
                "Eo vengan gatas pidan accion",
                "Voy azotarlas con tu reggaeton come on",
                "Eo \"(dale que yo aguanto la accion)",
                "si veras que saco presion presion"
            ],
            [
                "Eo dale duro dale duro (presion presion)",
                "Dale duro dale duro (presion presion)",
                "Eo dale duro dale duro (presion presion)",
                "Es-co-bar (presion presion)",
                "Eo dale duro dale duro (presion presion)",
                "Dale duro dale duro (presion presion)",
                "Eo dale duro dale duro (presion presion)"
            ],
            [
                "hey jajajaja",
                "Don.... segundo turno al bate",
                "Otro palo de Valentino",
                "Valen....tino",
                "Pirre otra produccion mas",
                "De los compadres..Alex",
                "Mario tu sabes..jaja",
                "Y en el abuso musikal",
                "El del contrabando Escobar junto a fade",
                "No les digas porque suenas tan duro (shh)",
                "Es nuestro secreto jajajaj",
                "Que no se asusten",
                "Que esto es fronteo con humildad",
                "Don y quien mas bandolero que nosotros?",
                "Dile Don (Compadres)"
            ]
        ]
    },
    {
        "author": "Valentino",
        "title": "Tu Vicio",
        "text": [
            [
                "(Solo te pido una noche mas)",
                "(Solo te pido una noche mas)",
                "(Solo te pido una noche mas)",
                "(Solo te pido...)"
            ],
            [
                "Lo niegues o no",
                "Soy el unico hombre que al oido te habla de amor",
                "(Te habla de amor)",
                "Tratamos de evitarlo pero el corazon nos traiciono",
                "(nos traiciono)",
                "Me eh convertido en tu vicio",
                "Why tu en mi obsecion",
                "Soy tu vicio",
                "Why tu mi obsecion",
                "Soy tu vicio",
                "Why tu mi obsecion",
                "(Valen-tino)",
                "(Divino)"
            ],
            [
                "Solo te pido una noche mas",
                "Para el deseo sacearlo no puedo evitar",
                "Solo te pido una noche mas",
                "Dame otra noche why no te hagas de rogar",
                "Solo te pido una noche mas",
                "Why cometer una locura por lo nuestro no esta mal",
                "Solo te pido una noche mas",
                "Eh! oh!"
            ],
            [
                "Es lamentable no tenerte en las noches",
                "Todo se debe a que no eres mi amante",
                "Se que en tus sueños has nelado tenerme",
                "Dime por que lo piensas para entregarte"
            ],
            [
                "why I'm sorry",
                "El amor es asi",
                "Nuestra alma es fuerte",
                "Que hare lucir debil",
                "Me tienes que decir",
                "No lo hagas dificil",
                "No ves que en las noches me la paso suplicando",
                "Why pidiendote ma'",
                "La oportunidad",
                "Para demostrar",
                "Que solo nesecito una noche mas",
                "Why al fin acabar con tanta soledad",
                "Dejate llevar por mi",
                "Pidiendote ma'",
                "La oportunidad",
                "Para demostrar",
                "Que solo nesecito una noche mas",
                "Why al fin acabar con tanta soledad",
                "Dejate llevar por mi"
            ],
            [
                "Solo te pido una noche mas",
                "Para el deseo sacearlo no puedo evitar",
                "Solo te pido una noche mas",
                "Dame otra noche why no te hagas de rogar",
                "Solo te pido una noche mas",
                "Que cometer una locura por lo nuestro no esta mal",
                "Solo te pido una noche mas",
                "Eh! oh!, (Eh! oh!...)"
            ],
            [
                "Tan solo te pido",
                "Contigo una noche",
                "Para demostrarte de que soy capas",
                "Quisiera tocarte",
                "De nuevo abrazarte",
                "Te juro que nunca lo vas a olvidar"
            ],
            [
                "Tan solo te pido",
                "Contigo una noche",
                "Para demostrarte de que soy capas",
                "Quisiera tocarte",
                "De nuevo abrazarte",
                "Te juro que nunca lo vas a olvidar"
            ],
            [
                "No lo vas a olvidar",
                "(No lo vas a olvidar)",
                "No lo vas a olvidar",
                "(No lo vas a olvidar)",
                "(oh!)"
            ],
            [
                "Solo te pido una noche mas",
                "Para el deseo sacearlo no puedo evitar",
                "Solo te pido una noche mas",
                "Dame otra noche why no te hagas de rogar",
                "Solo te pido una noche mas",
                "Que cometer una locura por lo nuestro no esta mal",
                "Solo te pido una noche mas",
                "Eh! oh!"
            ],
            [
                "Eliel",
                "Esto si que es letra",
                "Esto si que es musica",
                "Indiscutiblemente",
                "Uno de los Los Compadres",
                "Valen-tino",
                "Junto a",
                "Divino",
                "Oh Right!",
                "Dile Vale (jajaja)",
                "Temas como este",
                "Ingeniero",
                "(Dificil)",
                "Isma",
                "Mario",
                "Unos de los mejores compositores en este genero",
                "Tu sabes",
                "Compadres",
                "Los Compadres"
            ]
        ]
    },
    {
        "author": "Valentino",
        "title": "Ya lo Se",
        "text": [
            [
                "Magnate y Valentino",
                "Esto es sin limite",
                "Con el que habla con la fama",
                "El que pone a sandunguiar atodos esos latinos",
                "Eliel!!!!!"
            ],
            [
                "Ya lo se, que tu mirada choca on la mia",
                "Que con tu boca tu me besarias",
                "Que con tus besos tu me comerias",
                "Que a todos dices que es mentiras",
                "Porque el es otro amor que es tu dueño",
                "Que a ti te trata siempre con empeño",
                "Supuestamente otro amor eterno",
                "Y eso no me quita el sueño",
                "Pues mi nombre se te zafa al mirarlo a el ya lo se",
                "Y que mi voz es la que descontrola tu cuerpo",
                "Mami ya lo se"
            ],
            [
                "Ay...pero que ya lo se, ya lo",
                "Pero que ya lo se, ya lo",
                "Pero que ya lo se, que yo fui tuyo antes que el",
                "Nos fuimos",
                "Pero que ya lo se, ya lo",
                "Pero que ya lo se, ya lo",
                "Pero que ya lo se que yo fui tuyo antes que el"
            ],
            [
                "Corre y dile la verdad quel primero que fui yo",
                "Dale mai admitelo si en mi sientes soledad",
                "Aunque con el compartes mas",
                "Conmigo siempre la pasion",
                "Que hace que te entres tu al instante y sin pensar"
            ],
            [
                "Ay que otro nombre sientes agua al mirarlo a el ya lo se",
                "Y que mi voz que es la que descontrola tu cuerpo",
                "Mami ya lo se"
            ],
            [
                "Ya lo se que con tu mirada choca con la mia",
                "Que con tu boca tu me besarias",
                "Que con tus besos tu me comerias",
                "Que a todos dices que es mentiras",
                "Por que el ya es otro amor que es tu dueño",
                "Que a ti te trata siempre con empeño",
                "Supuestamente otro amor eterno",
                "Eso no me quita el sueño"
            ],
            [
                "Pues mi nombre se",
                "Te zafa al mirarlo a el",
                "Ya lo se",
                "Y que mi voz es la que descontrola tu cuerpo",
                "Mami",
                "Ya lo se"
            ],
            [
                "Ay!",
                "Pero que ya lo se ya lo",
                "Pero que ya lo se ya lo",
                "Pero que ya lo se",
                "Que yo fui tuyo antes que el",
                "Nos fuimos",
                "Pero que ya lo se ya lo",
                "Pero que ya lo se ya lo",
                "Pero que ya lo se",
                "Que yo fui tuyo antes que el"
            ],
            [
                "Que yo fui tuyo antes que el",
                "Que yo fui tuyo antes que el",
                "Esto es sin limites",
                "Que yo fui tuyo antes que el",
                "Que yo fui tuyo antes que el"
            ]
        ]
    }
]